adpipsvcfuncs/__init__.py
adpipsvcfuncs/adpipsvcfuncs.py
adpipsvcfuncs-0.1.14.dist-info/LICENSE
adpipsvcfuncs-0.1.14.dist-info/METADATA
adpipsvcfuncs-0.1.14.dist-info/WHEEL
adpipsvcfuncs-0.1.14.dist-info/top_level.txt
adpipsvcfuncs-0.1.14.dist-info/RECORD
